skinematics/.idea/.gitignore
skinematics/.idea/inspectionProfiles/profiles_settings.xml
skinematics/.idea/misc.xml
skinematics/.idea/modules.xml
skinematics/.idea/skinematics.iml
skinematics/.idea/vcs.xml
skinematics/__init__.py
skinematics/dummy.py
skinematics/imus.py
skinematics/markers.py
skinematics/misc.py
skinematics/quat.py
skinematics/rotmat.py
skinematics/sensors/__init__.py
skinematics/sensors/manual.py
skinematics/sensors/polulu.py
skinematics/sensors/xio.py
skinematics/sensors/xio3.py
skinematics/sensors/xio_ngimu.py
skinematics/sensors/xsens.py
skinematics/sensors/yei.py
skinematics/setup_old.py
skinematics/simulations/__init__.py
skinematics/simulations/simulate_movements.py
skinematics/vector.py
skinematics/view.py
tests/__init__.py
tests/data/data_ngimu/battery.csv
tests/data/data_ngimu/Device.xml
tests/data/data_ngimu/humidity.csv
tests/data/data_ngimu/quaternion.csv
tests/data/data_ngimu/rssi.csv
tests/data/data_ngimu/sensors.csv
tests/data/data_ngimu/Settings.txt
tests/data/data_ngimu/temperature.csv
tests/data/data_polulu.txt
tests/data/data_xio/00033.BIN
tests/data/data_xio/00033_CalBattAndTherm.csv
tests/data/data_xio/00033_CalInertialAndMag.csv
tests/data/data_xio/00033_Commands.csv
tests/data/data_xio/00033_DateTime.csv
tests/data/data_xio/00033_EulerAngles.csv
tests/data/data_xio/00033_Quaternion.csv
tests/data/data_xio/00033_Registers.csv
tests/data/data_xio/00033_RotationMatrix.csv
tests/data/data_xio3/Battery.csv
tests/data/data_xio3/Command.json
tests/data/data_xio3/HighGAccelerometer.csv
tests/data/data_xio3/Inertial.csv
tests/data/data_xio3/Magnetometer.csv
tests/data/data_xio3/Quaternion.csv
tests/data/data_xio3/Temperature.csv
tests/data/data_xsens.txt
tests/data/data_xsens2.txt
tests/data/data_yei.txt
tests/data/LeftFoot-marche01.c3d
tests/data/planet_trajectory_2D.txt
tests/data/walking_xsens_lowerLeg.txt
tests/data/walking_xsens_upperLeg.txt
tests/positive_rotations.py
tests/test_imus.py
tests/test_markers.py
tests/test_misc.py
scikit_kinematics-0.10.4.dist-info/LICENSE.txt
scikit_kinematics-0.10.4.dist-info/METADATA
scikit_kinematics-0.10.4.dist-info/WHEEL
scikit_kinematics-0.10.4.dist-info/RECORD
