Metadata-Version: 2.3
Name: scikit-kinematics
Version: 0.10.4
Summary: Python utilites for movements in 3d space
License: BSD-3-Clause
Keywords: quaterions,rotations
Author: Thomas Haslwanter
Author-email: thomas.haslwanter@fh-ooe.at
Requires-Python: >=3.9
Classifier: Development Status :: 4 - Beta
Classifier: Intended Audience :: Developers
Classifier: Intended Audience :: Science/Research
Classifier: License :: OSI Approved :: BSD License
Classifier: Programming Language :: Python :: 3
Classifier: Programming Language :: Python :: 3.9
Classifier: Programming Language :: Python :: 3.10
Classifier: Programming Language :: Python :: 3.11
Classifier: Programming Language :: Python :: 3.12
Classifier: Programming Language :: Python :: 3.13
Classifier: Topic :: Scientific/Engineering
Requires-Dist: docutils (>=0.3)
Requires-Dist: matplotlib (>3.9.1)
Requires-Dist: numpy (>=1.13.0)
Requires-Dist: pandas (>=1.0)
Requires-Dist: pygame (>=2.0)
Requires-Dist: scipy (>=1.5)
Requires-Dist: sympy (>=1.0)
Project-URL: Homepage, https://work.thaslwanter.at/skinematics/html
Project-URL: Repository, https://github.com/thomas-haslwanter/scikit-kinematics
